_versiointi_setuptools_build_meta.py
versiointi/__init__.py
versiointi/egg_info.py
versiointi/kaytanto.py
versiointi/oletus.py
versiointi/parametrit.py
versiointi/repo.py
versiointi/tiedostot.py
versiointi/vaatimukset.py
versiointi/versiointi.py
git_versiointi-1.6.dist-info/METADATA
git_versiointi-1.6.dist-info/WHEEL
git_versiointi-1.6.dist-info/entry_points.txt
git_versiointi-1.6.dist-info/historia.json
git_versiointi-1.6.dist-info/top_level.txt
git_versiointi-1.6.dist-info/RECORD
