Metadata-Version: 2.1
Name: git-versiointi
Version: 1.6
Summary: Asennettavan pakettiversion haku git-leimojen mukaan
Home-page: https://github.com/an7oine/git-versiointi.git
Author: Antti Hautaniemi
Author-email: antti.hautaniemi@pispalanit.fi
License: MIT
Classifier: Programming Language :: Python :: 3
Requires-Dist: GitPython
Requires-Dist: packaging
Requires-Dist: setuptools >=63
